{"batchcomplete":"","query":{"categorymembers":[{"pageid":4391531,"ns":0,"title":"The 5 Browns"},{"pageid":14207352,"ns":0,"title":"William Grant Bangerter"},{"pageid":39696924,"ns":0,"title":"Wilford Booth"},{"pageid":18030415,"ns":0,"title":"Fraser Bullock"},{"pageid":17860391,"ns":0,"title":"Jason Chaffetz"},{"pageid":5915217,"ns":0,"title":"Todd Christensen"},{"pageid":16206978,"ns":0,"title":"Tyler Haws"},{"pageid":48161667,"ns":0,"title":"Frank Jackson (basketball)"},{"pageid":41801095,"ns":0,"title":"Mike Kennedy (politician)"},{"pageid":25708300,"ns":0,"title":"Mike Lee (American politician)"},{"pageid":1779344,"ns":0,"title":"Gerald N. Lund"},{"pageid":5942374,"ns":0,"title":"Bronco Mendenhall"},{"pageid":37988015,"ns":0,"title":"John Rowe Moyle"},{"pageid":269991,"ns":0,"title":"Dale Murphy"},{"pageid":42556937,"ns":0,"title":"Orrin Olsen"},{"pageid":26008288,"ns":0,"title":"Morgan Philpot"},{"pageid":16803300,"ns":0,"title":"Dennis Smith (sculptor)"},{"pageid":9755238,"ns":0,"title":"Anita Stansfield"},{"pageid":28835206,"ns":0,"title":"M. May Booth Talmage"},{"pageid":50638399,"ns":0,"title":"May Booth Talmage"},{"pageid":51105633,"ns":0,"title":"Celestia Taylor"},{"pageid":6183796,"ns":0,"title":"Robert O. Young"}]}}