{"batchcomplete":"","query":{"categorymembers":[{"pageid":35064963,"ns":0,"title":"Helen Barnes"},{"pageid":22634360,"ns":0,"title":"John Beardsley"},{"pageid":40675699,"ns":0,"title":"Black-Eyed Susan (actress)"},{"pageid":21961522,"ns":0,"title":"Blackleach Burritt"},{"pageid":21401783,"ns":0,"title":"Dan Debicella"},{"pageid":5954033,"ns":0,"title":"James A. FitzPatrick"},{"pageid":11616914,"ns":0,"title":"Peter Leo Gerety"},{"pageid":14137268,"ns":0,"title":"Samuel B. Gould"},{"pageid":28390818,"ns":0,"title":"Harvey B. Hurd"},{"pageid":2686268,"ns":0,"title":"Dan Orlovsky"},{"pageid":42067481,"ns":0,"title":"Paul Pawlak Sr."},{"pageid":27216202,"ns":0,"title":"Faisal Shahzad"}]}}