{"batchcomplete":"","query":{"categorymembers":[{"pageid":39814140,"ns":0,"title":"List of people from Adrian, Michigan"},{"pageid":29364483,"ns":0,"title":"Rick Baxter"},{"pageid":7293217,"ns":0,"title":"William James Beal"},{"pageid":1008001,"ns":0,"title":"Fernando C. Beaman"},{"pageid":457798,"ns":0,"title":"Norman Bel Geddes"},{"pageid":24236199,"ns":0,"title":"Marcus Benard"},{"pageid":50893396,"ns":0,"title":"William K. Bixby"},{"pageid":3369878,"ns":0,"title":"Jerome B. Chaffee"},{"pageid":53494235,"ns":0,"title":"Myrtle Craig Mowbray"},{"pageid":14091187,"ns":0,"title":"Byron Darnton"},{"pageid":17108782,"ns":0,"title":"Kellen Davis"},{"pageid":10932929,"ns":0,"title":"Dorne Dibble"},{"pageid":32748167,"ns":0,"title":"Jack Feller"},{"pageid":34045811,"ns":0,"title":"Asahel Finch Jr."},{"pageid":31676272,"ns":0,"title":"Fritz Fisher"},{"pageid":11593681,"ns":0,"title":"Philo C. Fuller"},{"pageid":893301,"ns":0,"title":"Christine Gregoire"},{"pageid":42131448,"ns":0,"title":"Kevin R. Griffith"},{"pageid":53302016,"ns":0,"title":"John Hack"},{"pageid":43543587,"ns":0,"title":"Cornelius M. Hadley"},{"pageid":4269624,"ns":0,"title":"Tom Heckert Jr."},{"pageid":4513927,"ns":0,"title":"Jeff Hephner"},{"pageid":55459850,"ns":0,"title":"Primrose Rupp Hinton"},{"pageid":54297944,"ns":0,"title":"Andrew Holbrook"},{"pageid":3692649,"ns":0,"title":"Robert B. Howell"},{"pageid":1684778,"ns":0,"title":"Donald G. Jackson"},{"pageid":14136408,"ns":0,"title":"Rube Kisinger"},{"pageid":4693697,"ns":0,"title":"Nancy Kissel"},{"pageid":44843669,"ns":0,"title":"Matt Kohn"},{"pageid":58134571,"ns":0,"title":"Margaret Wynne Lawless"},{"pageid":2624482,"ns":0,"title":"Mike Marshall (pitcher)"},{"pageid":10913711,"ns":0,"title":"Orville D. Merillat"},{"pageid":3118595,"ns":0,"title":"Richard Merillat"},{"pageid":8827189,"ns":0,"title":"Earl C. Michener"},{"pageid":37767374,"ns":0,"title":"Vincent Mroz"},{"pageid":5335950,"ns":0,"title":"Frank Navin"},{"pageid":43575752,"ns":0,"title":"Lew Palmer"},{"pageid":48674014,"ns":0,"title":"William H. Payne"},{"pageid":9482053,"ns":0,"title":"Allen Potter"},{"pageid":44575027,"ns":0,"title":"James Royce Shannon"},{"pageid":8806036,"ns":0,"title":"Henry C. Smith"},{"pageid":28421090,"ns":0,"title":"Steven Threet"},{"pageid":6029579,"ns":0,"title":"Gregg Wager"},{"pageid":11368584,"ns":0,"title":"William H. Ward"},{"pageid":12469850,"ns":0,"title":"Bob Westfall"},{"pageid":50219045,"ns":0,"title":"Harvey A.K. Whitney"}]}}