{"batchcomplete":"","query":{"categorymembers":[{"pageid":31596973,"ns":0,"title":"Bob Armstrong (boxer)"},{"pageid":1068008,"ns":0,"title":"George L. Berry"},{"pageid":3227850,"ns":0,"title":"Charlie Chase (broadcaster)"},{"pageid":45038924,"ns":0,"title":"John M. Fleming"},{"pageid":32251655,"ns":0,"title":"Ken Givens"},{"pageid":29892362,"ns":0,"title":"Richard Hale"},{"pageid":3601533,"ns":0,"title":"Ruth Hale (feminist)"},{"pageid":209521,"ns":0,"title":"John N. Heiskell"},{"pageid":961037,"ns":0,"title":"Bill Jenkins (politician)"},{"pageid":4673019,"ns":0,"title":"Samuel Powell"},{"pageid":14710524,"ns":0,"title":"Joseph Rogers (pioneer)"},{"pageid":11570017,"ns":0,"title":"Bob Smith (pitcher, born 1895)"},{"pageid":3256065,"ns":0,"title":"Alexander P. Stewart"},{"pageid":26599302,"ns":0,"title":"Marcos Villatoro"},{"pageid":25760709,"ns":0,"title":"Jim White (wrestler)"}]}}