{"batchcomplete":"","query":{"categorymembers":[{"pageid":2559843,"ns":0,"title":"Roger Bowling"},{"pageid":48510516,"ns":0,"title":"Maxine Cheshire"},{"pageid":21810528,"ns":0,"title":"Karl Spillman Forester"},{"pageid":1855767,"ns":0,"title":"Bob Holman"},{"pageid":21096593,"ns":0,"title":"Edwin B. Howard"},{"pageid":7419370,"ns":0,"title":"Wallace Jones"},{"pageid":10566699,"ns":0,"title":"James E. Keller"},{"pageid":762775,"ns":0,"title":"Nick Lachey"},{"pageid":7572332,"ns":0,"title":"Cawood Ledford"},{"pageid":18117400,"ns":0,"title":"George Ella Lyon"},{"pageid":48648032,"ns":0,"title":"Jordan Smith (musician)"},{"pageid":54757841,"ns":0,"title":"Robert E. Wier"},{"pageid":8563294,"ns":0,"title":"Rusty York"}]}}