{"batchcomplete":"","query":{"categorymembers":[{"pageid":55366496,"ns":0,"title":"Jill Andrews"},{"pageid":28724049,"ns":0,"title":"Fred Archer (baseball)"},{"pageid":9018370,"ns":0,"title":"Bill Bain (consultant)"},{"pageid":19105163,"ns":0,"title":"Herman Beam"},{"pageid":43493977,"ns":0,"title":"Steven Berk"},{"pageid":12286754,"ns":0,"title":"Jerry Blevins"},{"pageid":21608571,"ns":0,"title":"John Bowers (writer)"},{"pageid":21585619,"ns":0,"title":"Ernie Bowman"},{"pageid":23641531,"ns":0,"title":"Joe Bowman (marksman)"},{"pageid":14585237,"ns":0,"title":"Dick Burleson"},{"pageid":15401420,"ns":0,"title":"Larry Butler (Canadian football)"},{"pageid":6894262,"ns":0,"title":"Jo Carson"},{"pageid":27436764,"ns":0,"title":"George Lafayette Carter"},{"pageid":11436182,"ns":0,"title":"David Cole (record producer)"},{"pageid":7066977,"ns":0,"title":"Bleu Copas"},{"pageid":50589142,"ns":0,"title":"Will Craig"},{"pageid":4501765,"ns":0,"title":"David Davis (U.S. politician)"},{"pageid":25490434,"ns":0,"title":"Terry Garland"},{"pageid":52451319,"ns":0,"title":"Wyck Godfrey"},{"pageid":20550463,"ns":0,"title":"Clarence Horton Greene"},{"pageid":2837471,"ns":0,"title":"Jake Grove"},{"pageid":57534754,"ns":0,"title":"Ben Hall (baseball)"},{"pageid":42328082,"ns":0,"title":"Holly Herndon"},{"pageid":8806641,"ns":0,"title":"Mark Herring"},{"pageid":8381217,"ns":0,"title":"Herman Hickman"},{"pageid":16170861,"ns":0,"title":"Jim Hickman (1910s outfielder)"},{"pageid":27982691,"ns":0,"title":"Mark Hurley"},{"pageid":5548388,"ns":0,"title":"Mark Jacoby"},{"pageid":53624089,"ns":0,"title":"Damon Johnson (basketball)"},{"pageid":21568950,"ns":0,"title":"Drew Johnson"},{"pageid":24730678,"ns":0,"title":"Clyde S. Kilby"},{"pageid":32804697,"ns":0,"title":"Paul Lewis (racing driver)"},{"pageid":50511337,"ns":0,"title":"Will Little III"},{"pageid":4549788,"ns":0,"title":"Catherine Marshall"},{"pageid":7953089,"ns":0,"title":"John Alan Maxwell"},{"pageid":26530345,"ns":0,"title":"Joe McClain"},{"pageid":5439736,"ns":0,"title":"Johnny Miller (racing driver)"},{"pageid":19458702,"ns":0,"title":"Jim Mooney (baseball)"},{"pageid":20925139,"ns":0,"title":"Jane Myron"},{"pageid":34829452,"ns":0,"title":"Daniel Norris (baseball)"},{"pageid":56663034,"ns":0,"title":"Eureka O'Hara"},{"pageid":3007603,"ns":0,"title":"Mike Potter (racing driver)"},{"pageid":20895391,"ns":0,"title":"Jim Preas"},{"pageid":4562913,"ns":0,"title":"Ron Ramsey"},{"pageid":18766171,"ns":0,"title":"Phil Roe (politician)"},{"pageid":39954386,"ns":0,"title":"Mo Sabri"},{"pageid":9074606,"ns":0,"title":"Connie Saylor"},{"pageid":5431375,"ns":0,"title":"Sam R. Sells"},{"pageid":41281278,"ns":0,"title":"Constance Shulman"},{"pageid":10974045,"ns":0,"title":"John Shulman"},{"pageid":1009794,"ns":0,"title":"Steve Spurrier"},{"pageid":37596735,"ns":0,"title":"Jenna Street"},{"pageid":2649722,"ns":0,"title":"Brad Teague"},{"pageid":38812452,"ns":0,"title":"Phyllis Tickle"},{"pageid":38341361,"ns":0,"title":"John Tipton (Tennessee)"},{"pageid":5251632,"ns":0,"title":"Ed Whitson"},{"pageid":10520726,"ns":0,"title":"Samuel Cole Williams"},{"pageid":13743940,"ns":0,"title":"Van Williams (American football)"},{"pageid":7631133,"ns":0,"title":"Seth Hartman Yocum"}]}}