{"batchcomplete":"","query":{"categorymembers":[{"pageid":2386589,"ns":0,"title":"Samuel Armas"},{"pageid":57816214,"ns":0,"title":"A. M. Cagle"},{"pageid":642704,"ns":0,"title":"Asa Griggs Candler"},{"pageid":3829499,"ns":0,"title":"Warren Akin Candler"},{"pageid":30345225,"ns":0,"title":"Jae Crowder"},{"pageid":181009,"ns":0,"title":"Thomas A. Dorsey"},{"pageid":27092097,"ns":0,"title":"Chris McCoy"},{"pageid":15915030,"ns":0,"title":"Hugh McGraw"},{"pageid":8516902,"ns":0,"title":"Rufus B. Nalley"},{"pageid":13008954,"ns":0,"title":"Ken Shackleford"},{"pageid":1564956,"ns":0,"title":"Dixie Walker"},{"pageid":9358626,"ns":0,"title":"Herman Weaver"},{"pageid":1894410,"ns":0,"title":"Ron Young (United States Army officer)"}]}}