{"batchcomplete":"","query":{"categorymembers":[{"pageid":1102381,"ns":0,"title":"John Allen (soldier)"},{"pageid":1504997,"ns":0,"title":"James Armstrong (Commodore)"},{"pageid":52905586,"ns":0,"title":"Priscilla Baird"},{"pageid":1868582,"ns":0,"title":"J. Franklin Bell"},{"pageid":15148948,"ns":0,"title":"Barney Bright"},{"pageid":1616224,"ns":0,"title":"Martha Layne Collins"},{"pageid":12026858,"ns":0,"title":"Patricia Cooksey"},{"pageid":11579304,"ns":0,"title":"Ralph Waldo Emerson Gilbert"},{"pageid":42682850,"ns":0,"title":"Paul Hornback"},{"pageid":45190217,"ns":0,"title":"Marshall Long"},{"pageid":5982279,"ns":0,"title":"Robert A. Long"},{"pageid":41521516,"ns":0,"title":"Betty Fible Martin"},{"pageid":45165813,"ns":0,"title":"Robert F. Matthews Jr."},{"pageid":11529194,"ns":0,"title":"Dan McGann"},{"pageid":42629737,"ns":0,"title":"Brad Montell"},{"pageid":4712192,"ns":0,"title":"Maurice Rabb Jr."},{"pageid":2905640,"ns":0,"title":"Alice Hegan Rice"},{"pageid":1326352,"ns":0,"title":"Buddy Ryan"},{"pageid":16580054,"ns":0,"title":"Robert Ryland"},{"pageid":17277457,"ns":0,"title":"Charles G. Shanks"},{"pageid":48912770,"ns":0,"title":"Jesse Sibley"},{"pageid":54493893,"ns":0,"title":"John Simpson (Kentucky)"},{"pageid":3047931,"ns":0,"title":"Augustus Owsley Stanley"},{"pageid":19576795,"ns":0,"title":"Lloyd Tevis"},{"pageid":36732237,"ns":0,"title":"George C. Tichenor"},{"pageid":5355977,"ns":0,"title":"Lee Tinsley"},{"pageid":19255519,"ns":0,"title":"Walter C. Whitaker"},{"pageid":11524756,"ns":0,"title":"Albert S. Willis"},{"pageid":2834253,"ns":0,"title":"Benjamin Wood"}]}}