{"batchcomplete":"","query":{"categorymembers":[{"pageid":58292798,"ns":0,"title":"Charles Albertine"},{"pageid":52911630,"ns":0,"title":"Michael F. Bachner"},{"pageid":30176772,"ns":0,"title":"Frank Baldino Jr."},{"pageid":50148878,"ns":0,"title":"Grace Banker"},{"pageid":31692048,"ns":0,"title":"George Baxter (lawyer)"},{"pageid":4882611,"ns":0,"title":"Terrence Boyle"},{"pageid":3561481,"ns":0,"title":"George Breeman"},{"pageid":12610199,"ns":0,"title":"John J. Byrne"},{"pageid":44491244,"ns":0,"title":"John J. Cali"},{"pageid":2900775,"ns":0,"title":"Arthur K. Cebrowski"},{"pageid":1406693,"ns":0,"title":"Morris Cerullo"},{"pageid":57545090,"ns":0,"title":"Stacy Cochran"},{"pageid":906423,"ns":0,"title":"Alan N. Cohen"},{"pageid":34058675,"ns":0,"title":"Ellen Dawson"},{"pageid":43733306,"ns":0,"title":"Edwin Decena"},{"pageid":27711953,"ns":0,"title":"Joel Diamond"},{"pageid":5670207,"ns":0,"title":"Evelyn Dubrow"},{"pageid":21989313,"ns":0,"title":"Bret Ernst"},{"pageid":42175611,"ns":0,"title":"Arthur Getz"},{"pageid":19413393,"ns":0,"title":"Hyman Golden"},{"pageid":45645299,"ns":0,"title":"Steven R. Goldstein"},{"pageid":30818786,"ns":0,"title":"Florence Greenberg"},{"pageid":43623359,"ns":0,"title":"Hezekiah Griggs"},{"pageid":41729343,"ns":0,"title":"Constance Endicott Hartt"},{"pageid":17769943,"ns":0,"title":"James Richard Haskell"},{"pageid":45556673,"ns":0,"title":"David Hirsch (rabbi)"},{"pageid":25728207,"ns":0,"title":"Paul J. Lioy"},{"pageid":20903769,"ns":0,"title":"Alex Lovy"},{"pageid":55206691,"ns":0,"title":"Fred R. Low"},{"pageid":55550723,"ns":0,"title":"Jonathan Maslow"},{"pageid":56122468,"ns":0,"title":"Mary Meriam"},{"pageid":57000394,"ns":0,"title":"Edwin D. Mott"},{"pageid":13828371,"ns":0,"title":"Joe Muscaglione"},{"pageid":10926716,"ns":0,"title":"Lester Novros"},{"pageid":3929050,"ns":0,"title":"Michael Marisi Ornstein"},{"pageid":2133638,"ns":0,"title":"David Packer"},{"pageid":1775968,"ns":0,"title":"Millie Perkins"},{"pageid":48216517,"ns":0,"title":"Eleanore Pettersen"},{"pageid":383864,"ns":0,"title":"Joe Piscopo"},{"pageid":185039,"ns":0,"title":"Michael J. Pollard"},{"pageid":7214441,"ns":0,"title":"Gerald J. Popek"},{"pageid":48624865,"ns":0,"title":"Nairoby Quezada"},{"pageid":55569332,"ns":0,"title":"Pamela Radcliff"},{"pageid":1181078,"ns":0,"title":"Alan Rosenberg"},{"pageid":20634734,"ns":0,"title":"Mark Rosenberg"},{"pageid":685608,"ns":0,"title":"Paul Rudd"},{"pageid":3470483,"ns":0,"title":"Bob Russell (television presenter)"},{"pageid":9584237,"ns":0,"title":"Yonason Sacks"},{"pageid":1713217,"ns":0,"title":"Zoe Saldana"},{"pageid":861011,"ns":0,"title":"Sherwood Schwartz"},{"pageid":33129985,"ns":0,"title":"William Winfield Scott"},{"pageid":23247967,"ns":0,"title":"Zalman Shapiro"},{"pageid":153161,"ns":0,"title":"Robert Smithson"},{"pageid":21832373,"ns":0,"title":"Sidney H. Stein"},{"pageid":2413931,"ns":0,"title":"Thomas Stockham"},{"pageid":3316423,"ns":0,"title":"Michael Stroka"},{"pageid":3721531,"ns":0,"title":"\u00d6sel Tendzin"},{"pageid":5111778,"ns":0,"title":"Franklin Van Antwerpen"},{"pageid":13928386,"ns":0,"title":"Ethel Wales"},{"pageid":900597,"ns":0,"title":"Liza Weil"},{"pageid":628230,"ns":0,"title":"Saul Zaentz"}]}}