{"batchcomplete":"","query":{"categorymembers":[{"pageid":5328835,"ns":0,"title":"William Cullom"},{"pageid":15872591,"ns":0,"title":"E. C. Duggins"},{"pageid":33327286,"ns":0,"title":"James Alexander Fowler"},{"pageid":21814121,"ns":0,"title":"Xenophon Hicks"},{"pageid":50414130,"ns":0,"title":"Trey Hollingsworth"},{"pageid":5387919,"ns":0,"title":"John C. Houk"},{"pageid":5372092,"ns":0,"title":"Leonidas C. Houk"},{"pageid":5974632,"ns":0,"title":"The McKameys"},{"pageid":11703730,"ns":0,"title":"Charles McRae"},{"pageid":37269008,"ns":0,"title":"Frank Justus Miller"},{"pageid":6445219,"ns":0,"title":"Carlos Moore"},{"pageid":43640209,"ns":0,"title":"Larry Seivers"},{"pageid":21977829,"ns":0,"title":"Johnny Stuart"},{"pageid":20762270,"ns":0,"title":"Tennessee Ramblers (Tennessee band)"},{"pageid":45263770,"ns":0,"title":"Paul Turner (pastor)"}]}}