{"batchcomplete":"","query":{"categorymembers":[{"pageid":4992709,"ns":0,"title":"Sade Aiyeku"},{"pageid":34517337,"ns":0,"title":"Adrienne Alexander"},{"pageid":5269882,"ns":0,"title":"Burl Barer"},{"pageid":36111361,"ns":0,"title":"Emilie Frances Bauer"},{"pageid":1454742,"ns":0,"title":"Marion Bauer"},{"pageid":14262993,"ns":0,"title":"Augustin-Magloire Blanchet"},{"pageid":3088231,"ns":0,"title":"Ralph P. Boas Jr."},{"pageid":26026981,"ns":0,"title":"Will Brandenburg"},{"pageid":40406914,"ns":0,"title":"Robert Brode"},{"pageid":42514746,"ns":0,"title":"Robert Clodius"},{"pageid":2323971,"ns":0,"title":"Tonya Cooley"},{"pageid":37902805,"ns":0,"title":"Ralph J. Cordiner"},{"pageid":41249851,"ns":0,"title":"C. Curtis-Smith"},{"pageid":27504701,"ns":0,"title":"Bill Gulick"},{"pageid":17900581,"ns":0,"title":"Cornelius H. Hanford"},{"pageid":3055553,"ns":0,"title":"Robert Hanson (United States Army Air Forces)"},{"pageid":46878959,"ns":0,"title":"Marion Jackson"},{"pageid":58558183,"ns":0,"title":"Gary Kent"},{"pageid":11180196,"ns":0,"title":"William R. King (judge)"},{"pageid":19610836,"ns":0,"title":"Douglas Kirby"},{"pageid":1617676,"ns":0,"title":"Dudley Wright Knox"},{"pageid":8641755,"ns":0,"title":"Leroy (musician)"},{"pageid":54494821,"ns":0,"title":"Russell McCormmach"},{"pageid":15074512,"ns":0,"title":"Daniel Moore (musician)"},{"pageid":5069938,"ns":0,"title":"Lee Moorhouse"},{"pageid":1409219,"ns":0,"title":"Edward P. Morgan"},{"pageid":23215458,"ns":0,"title":"John Mullan (road builder)"},{"pageid":2177566,"ns":0,"title":"Mikha'il Na'ima"},{"pageid":44614535,"ns":0,"title":"William Parker (screenwriter)"},{"pageid":48599335,"ns":0,"title":"Beverley Peck Johnson"},{"pageid":43684819,"ns":0,"title":"Kevin Pogue"},{"pageid":6991009,"ns":0,"title":"Charles Potts"},{"pageid":12551969,"ns":0,"title":"Don Roff"},{"pageid":24072042,"ns":0,"title":"Kenneth Rush"},{"pageid":11499383,"ns":0,"title":"Bill Schelly"},{"pageid":24722261,"ns":0,"title":"Schwabacher Brothers"},{"pageid":20998177,"ns":0,"title":"C. Arnholt Smith"},{"pageid":5994128,"ns":0,"title":"Hope Summers"},{"pageid":10175615,"ns":0,"title":"Mitch Traphagen"},{"pageid":657077,"ns":0,"title":"Connor Trinneer"},{"pageid":23277406,"ns":0,"title":"James Alexander Ulio"},{"pageid":160691,"ns":0,"title":"Jonathan M. Wainwright (general)"},{"pageid":5955066,"ns":0,"title":"Lemuel H. Wells"},{"pageid":278513,"ns":0,"title":"Adam West"},{"pageid":3636045,"ns":0,"title":"Robert Lee Yates"},{"pageid":269957,"ns":0,"title":"Hamza Yusuf"}]}}