{"batchcomplete":"","query":{"categorymembers":[{"pageid":21803897,"ns":0,"title":"John Watson Barr"},{"pageid":16283201,"ns":0,"title":"Jack Blackburn"},{"pageid":3704577,"ns":0,"title":"Johnson N. Camden Jr."},{"pageid":304107,"ns":0,"title":"Happy Chandler"},{"pageid":596966,"ns":0,"title":"Ben Chandler"},{"pageid":1616224,"ns":0,"title":"Martha Layne Collins"},{"pageid":2536629,"ns":0,"title":"John Conlee"},{"pageid":31190992,"ns":0,"title":"George Cruikshank (editor)"},{"pageid":41458811,"ns":0,"title":"Field Harris"},{"pageid":13137957,"ns":0,"title":"Mary Jane Holmes"},{"pageid":26428142,"ns":0,"title":"Josephine Henry"},{"pageid":41623428,"ns":0,"title":"Virginia Cary Hudson"},{"pageid":18577225,"ns":0,"title":"John T. Hughes"},{"pageid":19652990,"ns":0,"title":"Barry Irwin"},{"pageid":42582509,"ns":0,"title":"James Kay (Kentucky politician)"},{"pageid":36559857,"ns":0,"title":"Trey Kramer"},{"pageid":10955555,"ns":0,"title":"Thomas Francis Marshall"},{"pageid":50245344,"ns":0,"title":"Isham Railey McConnell"},{"pageid":22801473,"ns":0,"title":"MacKenzie Miller"},{"pageid":32076227,"ns":0,"title":"Noel F. Parrish"},{"pageid":2495570,"ns":0,"title":"Stephen S. Sawyer"},{"pageid":2168853,"ns":0,"title":"Charles Scott (governor)"},{"pageid":19008577,"ns":0,"title":"William Shatner"},{"pageid":10033368,"ns":0,"title":"William Walker (jockey)"}]}}