{"batchcomplete":"","query":{"categorymembers":[{"pageid":8457982,"ns":0,"title":"Bert Dingley"},{"pageid":975650,"ns":0,"title":"March Fong Eu"},{"pageid":10985344,"ns":0,"title":"Visco Grgich"},{"pageid":30483360,"ns":0,"title":"Troy Herriage"},{"pageid":42822465,"ns":0,"title":"Jennifer Lagier"},{"pageid":2914241,"ns":0,"title":"Eddie LeBaron"},{"pageid":54989617,"ns":0,"title":"Kelly McGill"},{"pageid":10165106,"ns":0,"title":"Eric Medlen"},{"pageid":46356368,"ns":0,"title":"Bob Pifferini Sr."},{"pageid":25306660,"ns":0,"title":"Jane Swagerty"}]}}