{"batchcomplete":"","query":{"categorymembers":[{"pageid":33792465,"ns":0,"title":"David Adams (baseball)"},{"pageid":2008016,"ns":0,"title":"Bobby Cannavale"},{"pageid":56677565,"ns":0,"title":"Sarah Chadwick (activist)"},{"pageid":7994517,"ns":0,"title":"Eric Eichmann"},{"pageid":32745711,"ns":0,"title":"Jonathan Freeny"},{"pageid":41598627,"ns":0,"title":"Arin Hanson"},{"pageid":46239205,"ns":0,"title":"Waheed Yar Khan"},{"pageid":26890013,"ns":0,"title":"Phillip Lamarre"},{"pageid":22836961,"ns":0,"title":"Al Lamberti"},{"pageid":12984330,"ns":0,"title":"Joe Lo Truglio"},{"pageid":17063958,"ns":0,"title":"Matt Luzunaris"},{"pageid":52403294,"ns":0,"title":"Michael Palardy"},{"pageid":38077204,"ns":0,"title":"Chase Rice"},{"pageid":46399662,"ns":0,"title":"Josh Smith (baseball)"}]}}