{"batchcomplete":"","query":{"categorymembers":[{"pageid":8258550,"ns":0,"title":"Dallas Baker"},{"pageid":46730577,"ns":0,"title":"Perry Baker"},{"pageid":5952894,"ns":0,"title":"Joseph Barbara (actor)"},{"pageid":8265487,"ns":0,"title":"Emory L. Bennett"},{"pageid":3425938,"ns":0,"title":"The Beu Sisters"},{"pageid":53538469,"ns":0,"title":"Ronald Blackwood"},{"pageid":50474537,"ns":0,"title":"Jacob Blankenship (basketball)"},{"pageid":15911910,"ns":0,"title":"Laura Brown (golfer)"},{"pageid":6178436,"ns":0,"title":"Wes Chandler"},{"pageid":33564787,"ns":0,"title":"Mike Crowder"},{"pageid":5539799,"ns":0,"title":"Joyce Cusack"},{"pageid":7123766,"ns":0,"title":"Darrell Fullington"},{"pageid":3151999,"ns":0,"title":"Chris Isaac"},{"pageid":18325011,"ns":0,"title":"Suzanne Kosmas"},{"pageid":35685541,"ns":0,"title":"Doris Marie Leeper"},{"pageid":24948401,"ns":0,"title":"Jimmy McMillan"},{"pageid":206635,"ns":0,"title":"Walter M. Miller Jr."},{"pageid":31248195,"ns":0,"title":"Jack Mitchell (photographer)"},{"pageid":34438832,"ns":0,"title":"Raheem Mostert"},{"pageid":21204227,"ns":0,"title":"Harold Nichols (American football)"},{"pageid":42170889,"ns":0,"title":"Jim Parsley"},{"pageid":50436882,"ns":0,"title":"Bob Ross"}]}}