{"batchcomplete":"","query":{"categorymembers":[{"pageid":6152769,"ns":0,"title":"Ted Barrett"},{"pageid":58134630,"ns":0,"title":"Peter Bos (rower)"},{"pageid":28090735,"ns":0,"title":"Cindy Bradley"},{"pageid":4199729,"ns":0,"title":"Jim Britton"},{"pageid":31680853,"ns":0,"title":"Rita Kogler Carver"},{"pageid":26007040,"ns":0,"title":"Maryalice Demler"},{"pageid":46648465,"ns":0,"title":"Elizabeth C. Hoffman"},{"pageid":7987536,"ns":0,"title":"Bret Hoffmann"},{"pageid":1252105,"ns":0,"title":"Jim Hurtubise"},{"pageid":31324563,"ns":0,"title":"Eugene de Kleist"},{"pageid":14689425,"ns":0,"title":"Edward C. Kuhn"},{"pageid":26006807,"ns":0,"title":"William Larson"},{"pageid":4137586,"ns":0,"title":"Robert Mangold"},{"pageid":4152877,"ns":0,"title":"George D. Maziarz"},{"pageid":48794336,"ns":0,"title":"Robert Ortt"},{"pageid":23995177,"ns":0,"title":"Gladys Parker"},{"pageid":37098089,"ns":0,"title":"Roman Piskor"},{"pageid":10814488,"ns":0,"title":"Stan Rojek"},{"pageid":7117897,"ns":0,"title":"Robin Schimminger"},{"pageid":30784511,"ns":0,"title":"Don Smith (rower)"},{"pageid":2721643,"ns":0,"title":"Paul Van Arsdale"},{"pageid":13563046,"ns":0,"title":"Christopher J. Waild"}]}}