{"batchcomplete":"","query":{"categorymembers":[{"pageid":47530827,"ns":0,"title":"Rebecca Anderson"},{"pageid":14238443,"ns":0,"title":"Dwight L. Armstrong"},{"pageid":20171418,"ns":0,"title":"William Barlow (pioneer)"},{"pageid":515823,"ns":0,"title":"Meredith Brooks"},{"pageid":12537688,"ns":0,"title":"Larry G. Dahl"},{"pageid":19431692,"ns":0,"title":"Eva Emery Dye"},{"pageid":13959832,"ns":0,"title":"Melville Eastham"},{"pageid":3980484,"ns":0,"title":"Philip Foster"},{"pageid":55121011,"ns":0,"title":"Thora B. Gardiner"},{"pageid":28830397,"ns":0,"title":"Randall Giles"},{"pageid":26992535,"ns":0,"title":"Lewis Hanke"},{"pageid":23714984,"ns":0,"title":"Felix Hathaway"},{"pageid":43588855,"ns":0,"title":"Sam Henry (musician)"},{"pageid":9065128,"ns":0,"title":"M. K. Hobson"},{"pageid":21814323,"ns":0,"title":"Michael Robert Hogan"},{"pageid":42088903,"ns":0,"title":"Lee Kelly"},{"pageid":2166169,"ns":0,"title":"Kenneth Scott Latourette"},{"pageid":553637,"ns":0,"title":"Edwin Markham"},{"pageid":41544,"ns":0,"title":"John McLoughlin"},{"pageid":27897085,"ns":0,"title":"John L. Morrison (pioneer)"},{"pageid":47653162,"ns":0,"title":"Wallace Mount"},{"pageid":28488366,"ns":0,"title":"Harrison Price"},{"pageid":3640158,"ns":0,"title":"Susan Ruttan"},{"pageid":1117238,"ns":0,"title":"Jeffrey St. Clair"},{"pageid":43603609,"ns":0,"title":"Drew Struzan"},{"pageid":29447442,"ns":0,"title":"Owen Wade (politician)"},{"pageid":11046316,"ns":0,"title":"Aaron E. Waite"},{"pageid":5181381,"ns":0,"title":"Ward Weaver III"}]}}