{"batchcomplete":"","query":{"categorymembers":[{"pageid":56552045,"ns":0,"title":"Ray Baum"},{"pageid":45561973,"ns":0,"title":"Jadin Bell"},{"pageid":4102428,"ns":0,"title":"Bucky Buckwalter"},{"pageid":54706647,"ns":0,"title":"Jason Eugene Bush"},{"pageid":1616075,"ns":0,"title":"Rod Chandler"},{"pageid":33383304,"ns":0,"title":"George Byron Currey"},{"pageid":1847864,"ns":0,"title":"Mitch Finley"},{"pageid":455861,"ns":0,"title":"Ron Gilbert"},{"pageid":11937495,"ns":0,"title":"Thomas G. Hailey"},{"pageid":23186342,"ns":0,"title":"Bob Herron"},{"pageid":53997198,"ns":0,"title":"Henry L. Hess"},{"pageid":5707232,"ns":0,"title":"Steve House (climber)"},{"pageid":34706147,"ns":0,"title":"John Hughes (counselor)"},{"pageid":1850345,"ns":0,"title":"Herbert Jasper"},{"pageid":14096721,"ns":0,"title":"Gail Kimbell"},{"pageid":41402095,"ns":0,"title":"John Lively (politician)"},{"pageid":8953689,"ns":0,"title":"Dallas McKennon"},{"pageid":55105793,"ns":0,"title":"Jackson L. Morrow"},{"pageid":2425484,"ns":0,"title":"Lee Morse"},{"pageid":4135207,"ns":0,"title":"John F. Nugent"},{"pageid":44093473,"ns":0,"title":"Mike Ragsdale"},{"pageid":11964299,"ns":0,"title":"William Marion Ramsey"},{"pageid":5226395,"ns":0,"title":"James H. Slater"},{"pageid":11955844,"ns":0,"title":"Woodson T. Slater"},{"pageid":56406448,"ns":0,"title":"Kay Cleaver Strahan"},{"pageid":19613510,"ns":0,"title":"Jack Ward Thomas"},{"pageid":18024617,"ns":0,"title":"Agnes Vernon"},{"pageid":29955510,"ns":0,"title":"John A. Warren"},{"pageid":53923114,"ns":0,"title":"Griff Williams (musician)"}]}}