{"batchcomplete":"","query":{"categorymembers":[{"pageid":48666772,"ns":0,"title":"Billy Brown (athlete)"},{"pageid":19134594,"ns":0,"title":"Ossie Brown"},{"pageid":25118654,"ns":0,"title":"Mike Cross (politician)"},{"pageid":25224219,"ns":0,"title":"W. W. Dumas"},{"pageid":9010232,"ns":0,"title":"Ken Ellis"},{"pageid":8830490,"ns":0,"title":"Hokie Gajan"},{"pageid":25218136,"ns":0,"title":"Pete Heine"},{"pageid":37708389,"ns":0,"title":"Reggie Jackson (basketball, born 1973)"},{"pageid":4748429,"ns":0,"title":"Victoria Nuland"},{"pageid":25261583,"ns":0,"title":"Bobby Simpson (Louisiana politician)"},{"pageid":46258473,"ns":0,"title":"Linda Thomas-Greenfield"},{"pageid":15836947,"ns":0,"title":"Jay Thomas (American football)"}]}}