{"batchcomplete":"","query":{"categorymembers":[{"pageid":11007744,"ns":0,"title":"Kate Aldrich"},{"pageid":3214073,"ns":0,"title":"Anna Belknap"},{"pageid":3558051,"ns":0,"title":"Bud Blake"},{"pageid":12401572,"ns":0,"title":"Charles A. Boutelle"},{"pageid":3172579,"ns":0,"title":"Glenn Chadbourne"},{"pageid":48673664,"ns":0,"title":"Hiram Chapman"},{"pageid":5912238,"ns":0,"title":"Barbara Cooney"},{"pageid":11177737,"ns":0,"title":"Edwin Flye"},{"pageid":11914287,"ns":0,"title":"Ezra B. French"},{"pageid":55312053,"ns":0,"title":"Lucy Hodgson"},{"pageid":35038533,"ns":0,"title":"Cordelia Hood"},{"pageid":7579395,"ns":0,"title":"Edward Kavanagh"},{"pageid":1563374,"ns":0,"title":"Hilton Kramer"},{"pageid":12804861,"ns":0,"title":"John D. McCrate"},{"pageid":17308251,"ns":0,"title":"Bob Page (blues musician)"},{"pageid":5023022,"ns":0,"title":"Frank Springer"},{"pageid":40784403,"ns":0,"title":"Betty Twarog"},{"pageid":30002073,"ns":0,"title":"Carleton Winslow"},{"pageid":21064193,"ns":0,"title":"Ola Elizabeth Winslow"},{"pageid":59000836,"ns":0,"title":"Charles Cushing Wright"}]}}