{"batchcomplete":"","query":{"categorymembers":[{"pageid":10471305,"ns":0,"title":"Charles Aberg"},{"pageid":12543120,"ns":0,"title":"Manny Babbitt"},{"pageid":9020511,"ns":0,"title":"John Clogston"},{"pageid":4947945,"ns":0,"title":"Stephen Cooper (American football)"},{"pageid":217702,"ns":0,"title":"Geena Davis"},{"pageid":31532747,"ns":0,"title":"Charles Decas"},{"pageid":5005945,"ns":0,"title":"Paul Fearing"},{"pageid":27312340,"ns":0,"title":"Susan Williams Gifford"},{"pageid":34385784,"ns":0,"title":"Leroy G\u00f3mez"},{"pageid":30773498,"ns":0,"title":"Warren Huston"},{"pageid":34832947,"ns":0,"title":"John Milton Mackie"},{"pageid":5500162,"ns":0,"title":"Donald W. Nicholson"},{"pageid":15336802,"ns":0,"title":"Jeff Olson (musician)"},{"pageid":31064466,"ns":0,"title":"Pebbles (radio personality)"},{"pageid":26735671,"ns":0,"title":"Jeff Perry (politician)"},{"pageid":2094442,"ns":0,"title":"Skipp Sudduth"},{"pageid":3127108,"ns":0,"title":"Zephaniah Swift"},{"pageid":57960882,"ns":0,"title":"Will Toffey"},{"pageid":9115735,"ns":0,"title":"Samuel T. Wellman"},{"pageid":33453728,"ns":0,"title":"Brandon Westgate"}]}}