{"batchcomplete":"","query":{"categorymembers":[{"pageid":40207794,"ns":0,"title":"Peleg Emory Aldrich"},{"pageid":3351988,"ns":0,"title":"David Oliver Allen"},{"pageid":42517533,"ns":0,"title":"Joseph Francis Barrett"},{"pageid":35790616,"ns":0,"title":"Samuel Bent"},{"pageid":5066015,"ns":0,"title":"Stephen Brewer"},{"pageid":38479160,"ns":0,"title":"Ebenezer Childs"},{"pageid":3965453,"ns":0,"title":"John Corrill"},{"pageid":21249930,"ns":0,"title":"Horatio Gates (businessman)"},{"pageid":37153332,"ns":0,"title":"William Augustus Hancock"},{"pageid":33336109,"ns":0,"title":"Martin Harty"},{"pageid":11594472,"ns":0,"title":"Timothy Jenkins"},{"pageid":3691316,"ns":0,"title":"Roger Langley"},{"pageid":11162317,"ns":0,"title":"Walker Lewis"},{"pageid":16754541,"ns":0,"title":"Joseph B. Plummer"},{"pageid":45355274,"ns":0,"title":"Robert V. Rice"},{"pageid":7005443,"ns":0,"title":"Daniel Ruggles"},{"pageid":9858073,"ns":0,"title":"John Smith (Vermont)"}]}}