{"batchcomplete":"","query":{"categorymembers":[{"pageid":4507629,"ns":0,"title":"Eliphalet Adams"},{"pageid":10842487,"ns":0,"title":"Weaver W. Adams"},{"pageid":18002,"ns":0,"title":"Louisa May Alcott"},{"pageid":23396228,"ns":0,"title":"John Allen (puritan)"},{"pageid":225956,"ns":0,"title":"Fisher Ames"},{"pageid":13186297,"ns":0,"title":"Nathaniel Ames"},{"pageid":7756045,"ns":0,"title":"Faxon Atherton"},{"pageid":18801960,"ns":0,"title":"Robert Joseph Banks"},{"pageid":10128009,"ns":0,"title":"John Andrew Barnes III"},{"pageid":28022845,"ns":0,"title":"Ebenezer Battelle"},{"pageid":24102656,"ns":0,"title":"Louis Brandeis"},{"pageid":8313600,"ns":0,"title":"Benjamin Bussey"},{"pageid":47805928,"ns":0,"title":"Charles W. Smith"},{"pageid":44573655,"ns":0,"title":"Hannah B. Chickering"},{"pageid":47805089,"ns":0,"title":"Chauncey C. Churchill"},{"pageid":45636151,"ns":0,"title":"Elizabeth Campbell Fisher Clay"},{"pageid":39533686,"ns":0,"title":"Deborah R. Cochran"},{"pageid":19583500,"ns":0,"title":"Waldo Colburn"},{"pageid":35470974,"ns":0,"title":"Warren Colburn"},{"pageid":1809270,"ns":0,"title":"LeBaron Bradford Colt"},{"pageid":25578769,"ns":0,"title":"Tim Costello (labor advocate)"},{"pageid":707575,"ns":0,"title":"Jacques d'Amboise (dancer)"},{"pageid":29895667,"ns":0,"title":"Buck Danner"},{"pageid":1737509,"ns":0,"title":"George Derby"},{"pageid":710809,"ns":0,"title":"Samuel Dexter"},{"pageid":44810151,"ns":0,"title":"Bill Doherty Jr."},{"pageid":3991811,"ns":0,"title":"Ted Donato"},{"pageid":11542920,"ns":0,"title":"Edward Dowse"},{"pageid":34930347,"ns":0,"title":"Warren Fales Draper (publisher)"},{"pageid":30630011,"ns":0,"title":"Dwight family"},{"pageid":11542243,"ns":0,"title":"Benjamin T. Eames"},{"pageid":1178942,"ns":0,"title":"Leon A. Edney"},{"pageid":10827806,"ns":0,"title":"Frederick D. Ely"},{"pageid":25680029,"ns":0,"title":"Augustus Bradford Endicott"},{"pageid":46520655,"ns":0,"title":"Henry Bradford Endicott"},{"pageid":46741042,"ns":0,"title":"Katherine Endicott"},{"pageid":50644105,"ns":0,"title":"Benjamin Fairbanks"},{"pageid":1145081,"ns":0,"title":"Jason Fairbanks"},{"pageid":8663388,"ns":0,"title":"Jonathan Fairbanks"},{"pageid":58395959,"ns":0,"title":"Henry Weston Farnsworth"},{"pageid":2680181,"ns":0,"title":"Alvan Fisher"},{"pageid":39161338,"ns":0,"title":"Denise Garlick"},{"pageid":13272304,"ns":0,"title":"William B. Gould I"},{"pageid":3567874,"ns":0,"title":"Reuben Guild"},{"pageid":31808944,"ns":0,"title":"David Hackett"},{"pageid":32316627,"ns":0,"title":"Lilian Westcott Hale"},{"pageid":3087824,"ns":0,"title":"Pete Hamilton"},{"pageid":34993036,"ns":0,"title":"Samuel Haven"},{"pageid":2623374,"ns":0,"title":"Amasa Hewins"},{"pageid":7600486,"ns":0,"title":"Connie Hines"},{"pageid":9512616,"ns":0,"title":"History of Dedham, Massachusetts, 1635\u20131792"},{"pageid":5784559,"ns":0,"title":"John Kiley (baseball)"},{"pageid":28937909,"ns":0,"title":"Maryanne Lewis"},{"pageid":656805,"ns":0,"title":"Reggie Lewis"},{"pageid":177530,"ns":0,"title":"Horace Mann"},{"pageid":52093825,"ns":0,"title":"Jerauld Newland Ezra Mann"},{"pageid":265836,"ns":0,"title":"John W. McCormack"},{"pageid":39538147,"ns":0,"title":"Charles M. McGowan"},{"pageid":36483389,"ns":0,"title":"Paul McMurtry"},{"pageid":28738019,"ns":0,"title":"Theron Metcalf"},{"pageid":54563513,"ns":0,"title":"Charles Mills (Massachusetts artist)"},{"pageid":21800970,"ns":0,"title":"Lefty Mills"},{"pageid":48488132,"ns":0,"title":"Marjorie Morrill"},{"pageid":227160,"ns":0,"title":"John Lothrop Motley"},{"pageid":39799510,"ns":0,"title":"Betty Jo Nelsen"},{"pageid":1396868,"ns":0,"title":"James W. Nicholson"},{"pageid":1397726,"ns":0,"title":"Samuel Nicholson"},{"pageid":49084305,"ns":0,"title":"Arthur S. Obermayer"},{"pageid":8385832,"ns":0,"title":"Peter H. Reynolds"},{"pageid":6267327,"ns":0,"title":"Freddie Roach (boxing)"},{"pageid":46754047,"ns":0,"title":"Harold Rosen (politician)"},{"pageid":45093606,"ns":0,"title":"Eli Sagan"},{"pageid":33930168,"ns":0,"title":"Mason Sears"},{"pageid":27379094,"ns":0,"title":"Thomas Sherwin"},{"pageid":1766674,"ns":0,"title":"Anita Shreve"},{"pageid":2834365,"ns":0,"title":"Frederic Jesup Stimson"},{"pageid":15110269,"ns":0,"title":"Richard Trethewey"},{"pageid":52926057,"ns":0,"title":"Tommy Vietor"},{"pageid":52252592,"ns":0,"title":"Winslow Warren"},{"pageid":8270036,"ns":0,"title":"Stephen Minot Weld Jr."},{"pageid":11543196,"ns":0,"title":"George F. Williams"},{"pageid":52094187,"ns":0,"title":"Rufus Corbin Wood"},{"pageid":56672002,"ns":0,"title":"John Yerxa"}]}}