{"batchcomplete":"","query":{"categorymembers":[{"pageid":33898004,"ns":0,"title":"Ethan B. Allen"},{"pageid":19437489,"ns":0,"title":"Mike Berniker"},{"pageid":11593898,"ns":0,"title":"Samuel Birdsall"},{"pageid":54229931,"ns":0,"title":"John Bunyan Bristol"},{"pageid":41959742,"ns":0,"title":"Squire S. Case"},{"pageid":11592995,"ns":0,"title":"Lot Clark"},{"pageid":11629652,"ns":0,"title":"Ezra Dean"},{"pageid":1329600,"ns":0,"title":"Madhur Jaffrey"},{"pageid":49637200,"ns":0,"title":"Henry Augustus Loop"},{"pageid":35842902,"ns":0,"title":"Robert L. D. Potter"},{"pageid":41316990,"ns":0,"title":"George N. Richmond"}]}}