{"batchcomplete":"","query":{"categorymembers":[{"pageid":6303441,"ns":0,"title":"Ayla Brown"},{"pageid":4161878,"ns":0,"title":"Scott Brown (politician)"},{"pageid":7059857,"ns":0,"title":"Jason Chandler"},{"pageid":18064900,"ns":0,"title":"George Park Fisher"},{"pageid":49047299,"ns":0,"title":"Charlotte W. Hawes"},{"pageid":46799090,"ns":0,"title":"Jake Layman"},{"pageid":41108692,"ns":0,"title":"Abraham Cressy Morrison"},{"pageid":29655481,"ns":0,"title":"Richard J. Ross"},{"pageid":2574217,"ns":0,"title":"Garth Snow"},{"pageid":20382501,"ns":0,"title":"Jon Syverson"},{"pageid":1631379,"ns":0,"title":"Preston Ware"}]}}