{"batchcomplete":"","query":{"categorymembers":[{"pageid":5910422,"ns":0,"title":"D. Wyatt Aiken"},{"pageid":1405702,"ns":0,"title":"Mike Anderson (running back)"},{"pageid":9084934,"ns":0,"title":"Webster Anderson"},{"pageid":12156939,"ns":0,"title":"John Bratton"},{"pageid":47378242,"ns":0,"title":"Theodore DuBose Bratton"},{"pageid":47329418,"ns":0,"title":"Robert Houston Curry"},{"pageid":45231816,"ns":0,"title":"Laura Douglas (artist)"},{"pageid":8404776,"ns":0,"title":"William Porcher DuBose"},{"pageid":28622137,"ns":0,"title":"William Ellison"},{"pageid":19912751,"ns":0,"title":"Gordon Glisson"},{"pageid":22698740,"ns":0,"title":"Justin Hobgood"},{"pageid":54501579,"ns":0,"title":"James Hooker (musician)"},{"pageid":15972494,"ns":0,"title":"Ellis Johnson (American football coach)"},{"pageid":53360898,"ns":0,"title":"William Zachariah Leitner"},{"pageid":54206085,"ns":0,"title":"Donnie Levister"},{"pageid":7464314,"ns":0,"title":"John Hugh Means"},{"pageid":1465866,"ns":0,"title":"Kelly Miller (scientist)"},{"pageid":23271874,"ns":0,"title":"James Milling"},{"pageid":5043233,"ns":0,"title":"Thomas J. Robertson"},{"pageid":3687978,"ns":0,"title":"Miriam Stevenson"},{"pageid":10996505,"ns":0,"title":"Tyler Thigpen"}]}}